Metadata-Version: 2.1
Name: odoo14-addon-account_invoice_line_sale_line_position
Version: 14.0.1.0.1.dev9
Summary: Adds the related sale line position on invoice line.
Home-page: https://github.com/OCA/account-invoice-reporting
Author: Camptocamp, Odoo Community Association (OCA)
Author-email: support@odoo-community.org
License: AGPL-3
Classifier: Programming Language :: Python
Classifier: Framework :: Odoo
Classifier: Framework :: Odoo :: 14.0
Classifier: License :: OSI Approved :: GNU Affero General Public License v3
Requires-Python: >=3.6
Requires-Dist: odoo14-addon-sale-order-line-position
Requires-Dist: odoo<14.1dev,>=14.0a
